{
  "type": "FeatureCollection",
  "features": {
    "type": "Feature",
    "id": {
      "type": "LineString",
      "coordinates": [
        [
          44.45792,
          48.794655
        ],
        [
          48.794655,
          44.45792
        ],
        [
          48.799793,
          44.455227
        ],
        [
          48.832085,
          44.420185
        ],
        [
          48.878685,
          44.316784
        ],
        [
          48.881504,
          44.312531
        ],
        [
          48.958282,
          44.217705
        ],
        [
          49.432709,
          43.896988
        ],
        [
          49.961769,
          43.314095
        ],
        [
          50.081596,
          43.146351
        ],
        [
          50.083527,
          43.144417
        ],
        [
          50.086197,
          43.141907
        ],
        [
          50.301048,
          42.880558
        ],
        [
          50.487953,
          42.662987
        ],
        [
          52.466335,
          41.36599
        ],
        [
          54.029617,
          39.313793
        ],
        [
          54.03088,
          39.312099
        ],
        [
          54.034019,
          39.307552
        ],
        [
          54.052628,
          39.27647
        ],
        [
          54.057419,
          39.269939
        ],
        [
          54.070545,
          39.252182
        ],
        [
          54.086964,
          39.229923
        ],
        [
          54.137634,
          39.160915
        ],
        [
          54.156628,
          39.135014
        ],
        [
          54.169617,
          39.118427
        ],
        [
          54.172222,
          39.116043
        ],
        [
          54.447418,
          38.592854
        ],
        [
          54.682266,
          38.322254
        ],
        [
          54.684402,
          38.321087
        ],
        [
          54.800678,
          38.083317
        ],
        [
          54.871208,
          38.028587
        ],
        [
          55.335892,
          37.775677
        ],
        [
          55.335125,
          37.768558
        ],
        [
          55.334793,
          37.76313
        ],
        [
          55.332603,
          37.672314
        ]
      ]
    },
    "geometry": null,
    "properties": {}
  }
}